Workbook

Sheet NFR Dataset
A1: NFR_ID | B1: Category | C1: Sub_Category | D1: Requirement | E1: Measurable_Target | F1: Priority | G1: MoSCoW | H1: Rationale | I1: How_Addressed_In_Design | J1: Test_Approach | K1: Owner | L1: Review_Frequency
A2: NFR-PERF-001 | B2: Performance | C2: Response Time | D2: API response time for search queries | E2: P95 < 500ms under normal load (100 concurrent users) | F2: Critical | G2: Must | H2: Store managers query prices throughout the trading day | I2: EF Core paginated queries with composite indexes + Redis cache (5-min TTL) | J2: Load test with k6: 100 VUs, assert P95 < 500ms | K2: Platform Team | L2: Quarterly
A3: NFR-PERF-002 | B3: Performance | C3: Throughput | D3: CSV upload processing — 10k rows | E3: Complete within 30 seconds end-to-end | F3: Critical | G3: Must | H3: Stores upload daily feeds before market open; delays affect trading | I3: EFCore.BulkExtensions MERGE upsert bypasses row-by-row EF tracking | J3: Performance test: upload 10k-row CSV, assert < 30s | K3: Platform Team | L3: Quarterly
A4: NFR-PERF-003 | B4: Performance | C4: Throughput | D4: CSV upload processing — 50k rows | E4: Complete within 120 seconds end-to-end | F4: High | G4: Must | H4: Larger stores (hypermarkets) carry 50k+ SKUs | I4: EFCore.BulkExtensions batch size 5000; async processing with progress tracking | J4: Performance test: upload 50k-row CSV, assert < 120s | K4: Platform Team | L4: Quarterly
A5: NFR-PERF-004 | B5: Performance | C5: Frontend | D5: Page load Time to Interactive | E5: < 3 seconds on simulated 4G connection | F5: High | G5: Must | H5: Store managers use a mix of desktop and tablet devices | I5: Webpack Module Federation lazy-loads MFEs; CDN edge caching of bundles | J5: Lighthouse CI: assert TTI < 3s on simulated 4G | K5: Frontend Team | L5: Quarterly
A6: NFR-PERF-005 | B6: Performance | C6: Database | D6: Paginated search query execution | E6: < 200ms P95 at 500 concurrent searches | F6: Critical | G6: Must | H6: Corporate analysts run bulk searches across all 3000 stores | I6: Composite index on (StoreId, Sku, EffectiveDate); covering indexes on filter columns | J6: Load test with k6: 500 VUs search queries, assert DB query time < 200ms | K6: DBA Team | L6: Monthly
A7: NFR-PERF-006 | B7: Performance | C7: Concurrency | D7: Simultaneous CSV upload sessions | E7: Support 500 concurrent uploads without degradation | F7: High | G7: Must | H7: All 3000 stores upload at similar times (morning shift start) | I7: Async MediatR pipeline; Azure Service Bus queue absorbs burst; horizontal API scaling | J7: Load test: 500 concurrent upload requests, assert no timeouts | K7: Platform Team | L7: Quarterly
A8: NFR-PERF-007 | B8: Performance | C8: Frontend | D8: Search results render time | E8: < 1 second from API response to visible rows | F8: Medium | G8: Should | H8: Analyst productivity depends on fast data exploration | I8: MUI DataGrid virtualised rendering; RTK Query caches prior results | J8: Synthetic monitor: measure render time via browser automation | K8: Frontend Team | L8: Quarterly
A9: NFR-PERF-008 | B9: Performance | C9: Throughput | D9: Bulk upsert database throughput | E9: Minimum 5000 rows/second sustained | F9: High | G9: Must | H9: Peak batch: 3000 stores × 100 rows = 300k rows within 1-hour window | I9: SQL Server MERGE via BulkExtensions; table partitioning by StoreId | J9: Throughput benchmark: insert 300k rows, measure rows/sec | K9: DBA Team | L9: Quarterly
A10: NFR-PERF-009 | B10: Performance | C10: Caching | D10: Redis cache hit ratio | E10: > 80% hit rate for repeated search queries | F10: Medium | G10: Should | H10: Analysts frequently repeat the same cross-store searches | I10: Redis distributed cache keyed by search parameters; 5-minute TTL | J10: Monitor cache hit ratio via Azure Cache for Redis metrics dashboard | K10: Platform Team | L10: Monthly
A11: NFR-PERF-010 | B11: Performance | C11: API Gateway | D11: API gateway sustained throughput | E11: 10000 requests/minute sustained for 1 hour | F11: High | G11: Must | H11: 3000 stores + analyst tools generate high API traffic | I11: Azure API Management with rate limiting and horizontal pod autoscaling | J11: Load test: sustain 10k req/min for 60 minutes, assert < 1% error rate | K11: Platform Team | L11: Quarterly
A12: NFR-SCAL-001 | B12: Scalability | C12: Compute | D12: API horizontal auto-scaling | E12: Scale from 2 to 20 pods within 3 minutes of load spike | F12: Critical | G12: Must | H12: Seasonal events (Black Friday) cause 10x traffic spikes | I12: Kubernetes HPA on CPU/memory; Azure Container Apps autoscale rules | J12: Chaos test: inject 10x load spike, assert scale-out within 3 minutes | K12: Platform Team | L12: Quarterly
... A69: NFR-CAP-004 | B69: Capacity | C69: API | D69: API response payload size | E69: Maximum response payload 5 MB; default page size 50 rows | F69: Medium | G69: Should | H69: Large payloads degrade mobile/low-bandwidth clients and increase latency | I69: Pagination enforced: max PageSize=200; hard cap in SearchQueryHandler | J69: Test: request PageSize=201; assert capped at 200 | K69: Platform Team | L69: Annually

Sheet Priority Matrix
A1: NFR_ID | B1: Category | C1: Business_Impact | D1: Technical_Complexity | E1: Priority_Score | F1: Quadrant
A2: NFR-PERF-001 | B2: Performance | C2: 5 | D2: 4 | E2: =C2*D2 | F2: =IF(AND(C2>=4,D2>=4),"Strategic Investment",IF(AND(C2>=4,D2<4),"Quick Win",IF(AND(C2<4,D2>=4),"Hard Problem","Low Priority")))
A3: NFR-PERF-002 | B3: Performance | C3: 5 | D3: 3 | E3: =C3*D3 | F3: =IF(AND(C3>=4,D3>=4),"Strategic Investment",IF(AND(C3>=4,D3<4),"Quick Win",IF(AND(C3<4,D3>=4),"Hard Problem","Low Priority")))
A4: NFR-PERF-003 | B4: Performance | C4: 4 | D4: 3 | E4: =C4*D4 | F4: =IF(AND(C4>=4,D4>=4),"Strategic Investment",IF(AND(C4>=4,D4<4),"Quick Win",IF(AND(C4<4,D4>=4),"Hard Problem","Low Priority")))
A5: NFR-PERF-004 | B5: Performance | C5: 4 | D5: 2 | E5: =C5*D5 | F5: =IF(AND(C5>=4,D5>=4),"Strategic Investment",IF(AND(C5>=4,D5<4),"Quick Win",IF(AND(C5<4,D5>=4),"Hard Problem","Low Priority")))
A6: NFR-PERF-005 | B6: Performance | C6: 5 | D6: 4 | E6: =C6*D6 | F6: =IF(AND(C6>=4,D6>=4),"Strategic Investment",IF(AND(C6>=4,D6<4),"Quick Win",IF(AND(C6<4,D6>=4),"Hard Problem","Low Priority")))
A7: NFR-PERF-006 | B7: Performance | C7: 4 | D7: 4 | E7: =C7*D7 | F7: =IF(AND(C7>=4,D7>=4),"Strategic Investment",IF(AND(C7>=4,D7<4),"Quick Win",IF(AND(C7<4,D7>=4),"Hard Problem","Low Priority")))
A8: NFR-PERF-007 | B8: Performance | C8: 3 | D8: 2 | E8: =C8*D8 | F8: =IF(AND(C8>=4,D8>=4),"Strategic Investment",IF(AND(C8>=4,D8<4),"Quick Win",IF(AND(C8<4,D8>=4),"Hard Problem","Low Priority")))
A9: NFR-PERF-008 | B9: Performance | C9: 5 | D9: 4 | E9: =C9*D9 | F9: =IF(AND(C9>=4,D9>=4),"Strategic Investment",IF(AND(C9>=4,D9<4),"Quick Win",IF(AND(C9<4,D9>=4),"Hard Problem","Low Priority")))
A10: NFR-PERF-009 | B10: Performance | C10: 3 | D10: 3 | E10: =C10*D10 | F10: =IF(AND(C10>=4,D10>=4),"Strategic Investment",IF(AND(C10>=4,D10<4),"Quick Win",IF(AND(C10<4,D10>=4),"Hard Problem","Low Priority")))
A11: NFR-PERF-010 | B11: Performance | C11: 4 | D11: 3 | E11: =C11*D11 | F11: =IF(AND(C11>=4,D11>=4),"Strategic Investment",IF(AND(C11>=4,D11<4),"Quick Win",IF(AND(C11<4,D11>=4),"Hard Problem","Low Priority")))
A12: NFR-SCAL-001 | B12: Scalability | C12: 5 | D12: 5 | E12: =C12*D12 | F12: =IF(AND(C12>=4,D12>=4),"Strategic Investment",IF(AND(C12>=4,D12<4),"Quick Win",IF(AND(C12<4,D12>=4),"Hard Problem","Low Priority")))
A13: NFR-SCAL-002 | B13: Scalability | C13: 4 | D13: 4 | E13: =C13*D13 | F13: =IF(AND(C13>=4,D13>=4),"Strategic Investment",IF(AND(C13>=4,D13<4),"Quick Win",IF(AND(C13<4,D13>=4),"Hard Problem","Low Priority")))
... A69: NFR-CAP-004 | B69: Capacity | C69: 3 | D69: 2 | E69: =C69*D69 | F69: =IF(AND(C69>=4,D69>=4),"Strategic Investment",IF(AND(C69>=4,D69<4),"Quick Win",IF(AND(C69<4,D69>=4),"Hard Problem","Low Priority")))

Sheet Category Summary
A1: Category | B1: Total_NFRs | C1: Critical_Count | D1: High_Count | E1: Medium_Count | F1: Low_Count | G1: Must_Count | H1: Should_Count | I1: Could_Count
A2: Performance | B2: =COUNTIF('NFR Dataset'!B:B,A2) | C2: =COUNTIFS('NFR Dataset'!B:B,A2,'NFR Dataset'!F:F,"Critical") | D2: =COUNTIFS('NFR Dataset'!B:B,A2,'NFR Dataset'!F:F,"High") | E2: =COUNTIFS('NFR Dataset'!B:B,A2,'NFR Dataset'!F:F,"Medium") | F2: =COUNTIFS('NFR Dataset'!B:B,A2,'NFR Dataset'!F:F,"Low") | G2: =COUNTIFS('NFR Dataset'!B:B,A2,'NFR Dataset'!G:G,"Must") | H2: =COUNTIFS('NFR Dataset'!B:B,A2,'NFR Dataset'!G:G,"Should") | I2: =COUNTIFS('NFR Dataset'!B:B,A2,'NFR Dataset'!G:G,"Could")
A3: Scalability | B3: =COUNTIF('NFR Dataset'!B:B,A3) | C3: =COUNTIFS('NFR Dataset'!B:B,A3,'NFR Dataset'!F:F,"Critical") | D3: =COUNTIFS('NFR Dataset'!B:B,A3,'NFR Dataset'!F:F,"High") | E3: =COUNTIFS('NFR Dataset'!B:B,A3,'NFR Dataset'!F:F,"Medium") | F3: =COUNTIFS('NFR Dataset'!B:B,A3,'NFR Dataset'!F:F,"Low") | G3: =COUNTIFS('NFR Dataset'!B:B,A3,'NFR Dataset'!G:G,"Must") | H3: =COUNTIFS('NFR Dataset'!B:B,A3,'NFR Dataset'!G:G,"Should") | I3: =COUNTIFS('NFR Dataset'!B:B,A3,'NFR Dataset'!G:G,"Could")
A4: Availability | B4: =COUNTIF('NFR Dataset'!B:B,A4) | C4: =COUNTIFS('NFR Dataset'!B:B,A4,'NFR Dataset'!F:F,"Critical") | D4: =COUNTIFS('NFR Dataset'!B:B,A4,'NFR Dataset'!F:F,"High") | E4: =COUNTIFS('NFR Dataset'!B:B,A4,'NFR Dataset'!F:F,"Medium") | F4: =COUNTIFS('NFR Dataset'!B:B,A4,'NFR Dataset'!F:F,"Low") | G4: =COUNTIFS('NFR Dataset'!B:B,A4,'NFR Dataset'!G:G,"Must") | H4: =COUNTIFS('NFR Dataset'!B:B,A4,'NFR Dataset'!G:G,"Should") | I4: =COUNTIFS('NFR Dataset'!B:B,A4,'NFR Dataset'!G:G,"Could")
A5: Security | B5: =COUNTIF('NFR Dataset'!B:B,A5) | C5: =COUNTIFS('NFR Dataset'!B:B,A5,'NFR Dataset'!F:F,"Critical") | D5: =COUNTIFS('NFR Dataset'!B:B,A5,'NFR Dataset'!F:F,"High") | E5: =COUNTIFS('NFR Dataset'!B:B,A5,'NFR Dataset'!F:F,"Medium") | F5: =COUNTIFS('NFR Dataset'!B:B,A5,'NFR Dataset'!F:F,"Low") | G5: =COUNTIFS('NFR Dataset'!B:B,A5,'NFR Dataset'!G:G,"Must") | H5: =COUNTIFS('NFR Dataset'!B:B,A5,'NFR Dataset'!G:G,"Should") | I5: =COUNTIFS('NFR Dataset'!B:B,A5,'NFR Dataset'!G:G,"Could")
A6: Compliance | B6: =COUNTIF('NFR Dataset'!B:B,A6) | C6: =COUNTIFS('NFR Dataset'!B:B,A6,'NFR Dataset'!F:F,"Critical") | D6: =COUNTIFS('NFR Dataset'!B:B,A6,'NFR Dataset'!F:F,"High") | E6: =COUNTIFS('NFR Dataset'!B:B,A6,'NFR Dataset'!F:F,"Medium") | F6: =COUNTIFS('NFR Dataset'!B:B,A6,'NFR Dataset'!F:F,"Low") | G6: =COUNTIFS('NFR Dataset'!B:B,A6,'NFR Dataset'!G:G,"Must") | H6: =COUNTIFS('NFR Dataset'!B:B,A6,'NFR Dataset'!G:G,"Should") | I6: =COUNTIFS('NFR Dataset'!B:B,A6,'NFR Dataset'!G:G,"Could")
A7: Observability | B7: =COUNTIF('NFR Dataset'!B:B,A7) | C7: =COUNTIFS('NFR Dataset'!B:B,A7,'NFR Dataset'!F:F,"Critical") | D7: =COUNTIFS('NFR Dataset'!B:B,A7,'NFR Dataset'!F:F,"High") | E7: =COUNTIFS('NFR Dataset'!B:B,A7,'NFR Dataset'!F:F,"Medium") | F7: =COUNTIFS('NFR Dataset'!B:B,A7,'NFR Dataset'!F:F,"Low") | G7: =COUNTIFS('NFR Dataset'!B:B,A7,'NFR Dataset'!G:G,"Must") | H7: =COUNTIFS('NFR Dataset'!B:B,A7,'NFR Dataset'!G:G,"Should") | I7: =COUNTIFS('NFR Dataset'!B:B,A7,'NFR Dataset'!G:G,"Could")
A8: Disaster Recovery | B8: =COUNTIF('NFR Dataset'!B:B,A8) | C8: =COUNTIFS('NFR Dataset'!B:B,A8,'NFR Dataset'!F:F,"Critical") | D8: =COUNTIFS('NFR Dataset'!B:B,A8,'NFR Dataset'!F:F,"High") | E8: =COUNTIFS('NFR Dataset'!B:B,A8,'NFR Dataset'!F:F,"Medium") | F8: =COUNTIFS('NFR Dataset'!B:B,A8,'NFR Dataset'!F:F,"Low") | G8: =COUNTIFS('NFR Dataset'!B:B,A8,'NFR Dataset'!G:G,"Must") | H8: =COUNTIFS('NFR Dataset'!B:B,A8,'NFR Dataset'!G:G,"Should") | I8: =COUNTIFS('NFR Dataset'!B:B,A8,'NFR Dataset'!G:G,"Could")
A9: Internationalisation | B9: =COUNTIF('NFR Dataset'!B:B,A9) | C9: =COUNTIFS('NFR Dataset'!B:B,A9,'NFR Dataset'!F:F,"Critical") | D9: =COUNTIFS('NFR Dataset'!B:B,A9,'NFR Dataset'!F:F,"High") | E9: =COUNTIFS('NFR Dataset'!B:B,A9,'NFR Dataset'!F:F,"Medium") | F9: =COUNTIFS('NFR Dataset'!B:B,A9,'NFR Dataset'!F:F,"Low") | G9: =COUNTIFS('NFR Dataset'!B:B,A9,'NFR Dataset'!G:G,"Must") | H9: =COUNTIFS('NFR Dataset'!B:B,A9,'NFR Dataset'!G:G,"Should") | I9: =COUNTIFS('NFR Dataset'!B:B,A9,'NFR Dataset'!G:G,"Could")
A10: Maintainability | B10: =COUNTIF('NFR Dataset'!B:B,A10) | C10: =COUNTIFS('NFR Dataset'!B:B,A10,'NFR Dataset'!F:F,"Critical") | D10: =COUNTIFS('NFR Dataset'!B:B,A10,'NFR Dataset'!F:F,"High") | E10: =COUNTIFS('NFR Dataset'!B:B,A10,'NFR Dataset'!F:F,"Medium") | F10: =COUNTIFS('NFR Dataset'!B:B,A10,'NFR Dataset'!F:F,"Low") | G10: =COUNTIFS('NFR Dataset'!B:B,A10,'NFR Dataset'!G:G,"Must") | H10: =COUNTIFS('NFR Dataset'!B:B,A10,'NFR Dataset'!G:G,"Should") | I10: =COUNTIFS('NFR Dataset'!B:B,A10,'NFR Dataset'!G:G,"Could")
A11: Capacity | B11: =COUNTIF('NFR Dataset'!B:B,A11) | C11: =COUNTIFS('NFR Dataset'!B:B,A11,'NFR Dataset'!F:F,"Critical") | D11: =COUNTIFS('NFR Dataset'!B:B,A11,'NFR Dataset'!F:F,"High") | E11: =COUNTIFS('NFR Dataset'!B:B,A11,'NFR Dataset'!F:F,"Medium") | F11: =COUNTIFS('NFR Dataset'!B:B,A11,'NFR Dataset'!F:F,"Low") | G11: =COUNTIFS('NFR Dataset'!B:B,A11,'NFR Dataset'!G:G,"Must") | H11: =COUNTIFS('NFR Dataset'!B:B,A11,'NFR Dataset'!G:G,"Should") | I11: =COUNTIFS('NFR Dataset'!B:B,A11,'NFR Dataset'!G:G,"Could")
A12: TOTALS | B12: =SUM(B2:B11) | C12: =SUM(C2:C11) | D12: =SUM(D2:D11) | E12: =SUM(E2:E11) | F12: =SUM(F2:F11) | G12: =SUM(G2:G11) | H12: =SUM(H2:H11) | I12: =SUM(I2:I11)

Sheet Test Approach Register
A1: Category | B1: Test_Type | C1: Tooling | D1: Frequency | E1: Pass_Criteria | F1: Responsible_Team
A2: Performance | B2: Load & Performance Testing | C2: k6, JMeter, Gatling | D2: Per release + quarterly benchmark | E2: P95 response < 500ms; 50k upload < 120s; throughput > 5000 rows/sec | F2: Platform Team
A3: Scalability | B3: Chaos Engineering & Load Simulation | C3: Azure Chaos Studio, k6, Locust | D3: Quarterly; annually for geo tests | E3: Scale-out within 3 minutes; no SLA breach at 10x load for 48 hours | F3: Platform Team
A4: Availability | B4: Synthetic Monitoring & DR Drills | C4: Azure Application Insights Availability Tests, PagerDuty | D4: Synthetic: every 5 minutes; DR drills: quarterly | E4: 99.9% uptime; RTO < 1 hour; RPO < 15 minutes confirmed per drill | F4: Platform Team
A5: Security | B5: Penetration Testing, SAST, DAST | C5: OWASP ZAP, truffleHog, Dependabot, manual pen test | D5: SAST/DAST: every CI build; pen test: annually | E5: Zero critical/high unmitigated findings; SSL Labs A+; no secrets in repo | F5: Security Team
A6: Compliance | B6: Compliance Audit & Policy Verification | C6: Azure Policy, manual GDPR/CCPA review, axe-core | D6: Annually for regulatory; quarterly for accessibility | E6: All rights-to-erasure fulfilled in time; AU data residency confirmed; WCAG 2.1 AA pass | F6: Compliance Team
A7: Observability | B7: Log Verification, Alert Testing, Dashboard Review | C7: Application Insights, Azure Monitor, PagerDuty | D7: Monthly alert tests; quarterly dashboard review | E7: 100% request log coverage; P1 page < 5 minutes; error-rate alert fires within 5 minutes | F7: Platform Team
A8: Disaster Recovery | B8: Failover Drill & Backup Restore Test | C8: Azure SQL Failover Group, Azure Automation, manual restore | D8: Quarterly DR drills; monthly backup restore verification | E8: Failover < 30 seconds; RPO confirmed < 15 minutes; backup restore succeeds | F8: Platform Team / DBA Team
A9: Internationalisation | B9: Locale & Timezone Unit and Integration Tests | C9: xUnit, React Testing Library, react-intl | D9: Per release | E9: Correct currency, date format, decimal separator per locale; UTC stored correctly | F9: Frontend Team / Platform Team
A10: Maintainability | B10: Code Coverage Gate, Contract Tests, MTTR Tracking | C10: coverlet, Pact, Azure DevOps Boards | D10: CI: every build; MTTR: monthly review | E10: Coverage >= 80%; no breaking contract violations; MTTR P1 < 2 hours | F10: Engineering Team
A11: Capacity | B11: Capacity & Volume Benchmarks | C11: Custom SQL scripts, k6, Azure Monitor | D11: Quarterly for DB capacity; annually for file size limits | E11: 50M records with P95 search < 500ms; 3000 uploads within 2 hours; 10MB limit enforced | F11: DBA Team / Platform Team
